cobol_copybook_to_json/__init__.py
cobol_copybook_to_json-1.1.1.dist-info/licenses/LICENSE
cobol_copybook_to_json-1.1.1.dist-info/METADATA
cobol_copybook_to_json-1.1.1.dist-info/WHEEL
cobol_copybook_to_json-1.1.1.dist-info/entry_points.txt
cobol_copybook_to_json-1.1.1.dist-info/top_level.txt
cobol_copybook_to_json-1.1.1.dist-info/RECORD
