Metadata-Version: 2.4
Name: cobol-copybook-to-json
Version: 1.1.1
Summary: Convert COBOL copybooks to JSON schema format
Home-page: https://github.com/arunkumars-mf/cobol-copybook-to-json
Author: Arunkumar Selvam
Author-email: Arunkumar Selvam <aruninfy123@gmail.com>
License-Expression: MIT
Project-URL: Homepage, https://github.com/arunkumars-mf/cobol-copybook-to-json
Project-URL: Bug Reports, https://github.com/arunkumars-mf/cobol-copybook-to-json/issues
Project-URL: Source, https://github.com/arunkumars-mf/cobol-copybook-to-json
Project-URL: Citation, https://github.com/arunkumars-mf/cobol-copybook-to-json/blob/main/CITATION.cff
Keywords: cobol,copybook,json,schema,converter,mainframe
Classifier: Development Status :: 4 - Beta
Classifier: Intended Audience :: Developers
Classifier: Topic :: Software Development :: Libraries :: Python Modules
Classifier: Topic :: Text Processing :: Markup :: XML
Classifier: Programming Language :: Python :: 3
Classifier: Programming Language :: Python :: 3.7
Classifier: Programming Language :: Python :: 3.8
Classifier: Programming Language :: Python :: 3.9
Classifier: Programming Language :: Python :: 3.10
Classifier: Programming Language :: Python :: 3.11
Classifier: Programming Language :: Python :: 3.12
Requires-Python: >=3.7
License-File: LICENSE
Dynamic: author
Dynamic: home-page
Dynamic: license-file
Dynamic: requires-python
